langsfer/__init__.py
langsfer/alignment.py
langsfer/constants.py
langsfer/embeddings.py
langsfer/high_level.py
langsfer/initialization.py
langsfer/py.typed
langsfer/similarity.py
langsfer/token_overlap.py
langsfer/utils.py
langsfer/weights.py
langsfer-0.1.0.dist-info/LICENSE
langsfer-0.1.0.dist-info/METADATA
langsfer-0.1.0.dist-info/WHEEL
langsfer-0.1.0.dist-info/RECORD
