Metadata-Version: 2.1
Name: langsfer
Version: 0.1.0
Summary: A library for language transfer methods and algorithms. 
Home-page: https://github.com/AnesBenmerzoug/langsfer
License: LGPL-2.1-only
Author: Anes Benmerzoug
Author-email: anes.benmerzoug@gmail.com
Requires-Python: >=3.10,<3.13
Classifier: Development Status :: 4 - Beta
Classifier: Intended Audience :: Science/Research
Classifier: License :: OSI Approved
Classifier: Programming Language :: Python
Classifier: Programming Language :: Python :: 3
Classifier: Programming Language :: Python :: 3.10
Classifier: Programming Language :: Python :: 3.11
Classifier: Programming Language :: Python :: 3.12
Classifier: Programming Language :: Python :: Implementation :: CPython
Classifier: Programming Language :: Python :: Implementation :: PyPy
Classifier: Topic :: Scientific/Engineering :: Artificial Intelligence
Classifier: Topic :: Software Development :: Libraries :: Python Modules
Requires-Dist: gensim (>=4.3.0,<5.0.0)
Requires-Dist: more-itertools (>=10.5.0,<11.0.0)
Requires-Dist: numpy (<2.0.0)
Requires-Dist: scikit-learn (>=1.2.0,<2.0.0)
Requires-Dist: scipy (<1.13)
Requires-Dist: torch (>=2.0.0,<3.0.0)
Requires-Dist: transformers (>=4.26.0,<5.0.0)
Project-URL: Repository, https://github.com/AnesBenmerzoug/langsfer
